poetry_relax/__init__.py
poetry_relax/_core.py
poetry_relax/command.py
poetry_relax/py.typed
poetry_relax-1.1.0.dist-info/LICENSE
poetry_relax-1.1.0.dist-info/METADATA
poetry_relax-1.1.0.dist-info/WHEEL
poetry_relax-1.1.0.dist-info/entry_points.txt
poetry_relax-1.1.0.dist-info/RECORD
