Metadata-Version: 2.1
Name: poetry-relax
Version: 1.1.0
Summary: Plugin for Poetry to relax upper version pins
Home-page: https://github.com/madkinsz/poetry-relax
Keywords: poetry,plugin,versioning,version
Author: Zanie
Author-email: contact@zanie.dev
Requires-Python: >=3.8,<4.0
Classifier: Development Status :: 3 - Alpha
Classifier: Environment :: Plugins
Classifier: Intended Audience :: Developers
Classifier: License :: OSI Approved :: MIT License
Classifier: Natural Language :: English
Classifier: Operating System :: OS Independent
Classifier: Programming Language :: Python
Classifier: Programming Language :: Python :: 3
Classifier: Programming Language :: Python :: 3.8
Classifier: Programming Language :: Python :: 3.9
Classifier: Programming Language :: Python :: 3.10
Classifier: Programming Language :: Python :: 3.11
Classifier: Programming Language :: Python :: 3.12
Classifier: Programming Language :: Python :: 3.7
Classifier: Topic :: Software Development
Classifier: Topic :: Software Development :: Libraries
Classifier: Typing :: Typed
Requires-Dist: poetry (>=1.2)
Project-URL: Repository, https://github.com/madkinsz/poetry-relax
